ElasticSearchSparkLoader/__init__.py
ElasticSearchSparkLoader-1.0.2.dist-info/LICENSE
ElasticSearchSparkLoader-1.0.2.dist-info/METADATA
ElasticSearchSparkLoader-1.0.2.dist-info/WHEEL
ElasticSearchSparkLoader-1.0.2.dist-info/top_level.txt
ElasticSearchSparkLoader-1.0.2.dist-info/RECORD
